README
setup.py
./__init__.py
./health_ems.py
./health_ems_view.xml
./tryton.cfg
./data/health_ems_sequence.xml
./doc/index.rst
./icons/ambulance.svg
./icons/operator.svg
./locale/ar.po
./locale/de.po
./locale/el.po
./locale/es.po
./locale/fr.po
./locale/it_IT.po
./locale/ja_JP.po
./locale/lo.po
./locale/pt_BR.po
./locale/zh_CN.po
./tests/__init__.py
./tests/test_health_ems.py
./view/ambulance_form.xml
./view/ambulance_healthprofessional_form.xml
./view/ambulance_healthprofessional_tree.xml
./view/ambulance_support_form.xml
./view/ambulance_support_tree.xml
./view/ambulance_tree.xml
./view/support_request_form.xml
./view/support_request_log_form.xml
./view/support_request_log_tree.xml
./view/support_request_tree.xml
trytond_health_ems.egg-info/PKG-INFO
trytond_health_ems.egg-info/SOURCES.txt
trytond_health_ems.egg-info/dependency_links.txt
trytond_health_ems.egg-info/entry_points.txt
trytond_health_ems.egg-info/not-zip-safe
trytond_health_ems.egg-info/requires.txt
trytond_health_ems.egg-info/top_level.txt